hpyculator/__init__.py
hpyculator-1.0.3.dist-info/LICENSE.txt
hpyculator-1.0.3.dist-info/METADATA
hpyculator-1.0.3.dist-info/WHEEL
hpyculator-1.0.3.dist-info/top_level.txt
hpyculator-1.0.3.dist-info/RECORD
