Metadata-Version: 2.1
Name: hpyculator
Version: 1.0.3
Summary: 这是一个基于python的可编程计算器
Home-page: https://github.com/pypa/sampleproject
Author: HowieHz
License: UNKNOWN
Project-URL: Bug Reports, https://github.com/HowieHz/hpyculatorPackage/issues
Platform: UNKNOWN
Classifier: License :: OSI Approved :: GNU Affero General Public License v3 or later (AGPLv3+)
Classifier: Operating System :: OS Independent
Classifier: Programming Language :: Python :: 3.6
Classifier: Programming Language :: Python :: 3.7
Classifier: Programming Language :: Python :: 3.8
Classifier: Programming Language :: Python :: 3.9
License-File: LICENSE.txt
Requires-Dist: wxpython
